crossproductinverse/__init__.py
crossproductinverse/main.py
crossproductinverse/utils.py
crossproductinverse-0.1.0.dist-info/METADATA
crossproductinverse-0.1.0.dist-info/WHEEL
crossproductinverse-0.1.0.dist-info/top_level.txt
crossproductinverse-0.1.0.dist-info/RECORD
