Metadata-Version: 2.4
Name: crossproductinverse
Version: 0.1.0
Summary: Compute the inverse of the cross-product for 3D vectors.
Home-page: https://github.com/yourusername/CrossProductInverse
Author: Leon Deligny
Author-email: leon.deligny@icloud.com
Classifier: Programming Language :: Python :: 3
Classifier: Operating System :: OS Independent
Classifier: License :: OSI Approved :: MIT License
Classifier: Intended Audience :: Science/Research
Classifier: Topic :: Scientific/Engineering :: Mathematics
Requires-Python: >=3.0
Requires-Dist: numpy
Dynamic: author
Dynamic: author-email
Dynamic: classifier
Dynamic: description
Dynamic: description-content-type
Dynamic: home-page
Dynamic: requires-dist
Dynamic: requires-python
Dynamic: summary
